tamilmorph/ThamizhiLP.py
tamilmorph/__init__.py
tamilmorph/analyser.py
tamilmorph/fsts/noun-guesser.fst
tamilmorph/fsts/noun.fst
tamilmorph/fsts/verb-guesser.fst
tamilmorph/fsts/verbs-rest.fst
tamilmorph/fsts/verbs11.fst
tamilmorph/fsts/verbs12.fst
tamilmorph/fsts/verbs3.fst
tamilmorph/fsts/verbs4.fst
tamilmorph/fsts/verbs62.fst
tamilmorph-0.93.dist-info/LICENSE
tamilmorph-0.93.dist-info/METADATA
tamilmorph-0.93.dist-info/WHEEL
tamilmorph-0.93.dist-info/top_level.txt
tamilmorph-0.93.dist-info/RECORD
