Metadata-Version: 2.1
Name: tamilmorph
Version: 0.93
Summary: A FST based Morphological analyser and generator for Tamil
Home-page: https://github.com/sarves/thamizhi-morph
Author: Kengatharaiyer Sarveswaran
Author-email: sarvesk@uom.lk
License: UNKNOWN
Platform: UNKNOWN
Classifier: Development Status :: 3 - Alpha
Classifier: Programming Language :: Python :: 3
Classifier: License :: OSI Approved :: Apache Software License
Classifier: Operating System :: OS Independent
Classifier: Natural Language :: Tamil
Requires-Python: >=3.6
